ansys/scade/design_rules/__init__.py
ansys/scade/design_rules/catalog.txt
ansys/scade/design_rules/annotations/ann_note_connected_data_for_public_interface.py
ansys/scade/design_rules/annotations/ann_notes_for_basic_datatypes_in_structures.py
ansys/scade/design_rules/annotations/ann_notes_for_basic_interface_types.py
ansys/scade/design_rules/annotations/ann_notes_for_named_types_or_variables.py
ansys/scade/design_rules/annotations/ann_notes_present_and_not_empty.py
ansys/scade/design_rules/annotations/comment_has_specific_headlines.py
ansys/scade/design_rules/annotations/identical_for_producer_consumer.py
ansys/scade/design_rules/case/default_case.py
ansys/scade/design_rules/case/enum_has_default_case.py
ansys/scade/design_rules/case/statemachine_has_default_state.py
ansys/scade/design_rules/configuration/check_configuration.py
ansys/scade/design_rules/configuration/check_configuration_custom1.py
ansys/scade/design_rules/diagrams/elements_within_area.py
ansys/scade/design_rules/diagrams/page_format.py
ansys/scade/design_rules/diagrams/textual_diagrams.py
ansys/scade/design_rules/metrics/level_of_packages.py
ansys/scade/design_rules/metrics/number_of_diagrams_per_element.py
ansys/scade/design_rules/metrics/number_of_nested_activate_blocks.py
ansys/scade/design_rules/metrics/number_of_nested_sms.py
ansys/scade/design_rules/metrics/number_of_operators_per_package.py
ansys/scade/design_rules/metrics/number_of_outgoing_transitions_per_state.py
ansys/scade/design_rules/metrics/number_of_predef_ops_in_diagram.py
ansys/scade/design_rules/metrics/number_of_user_ops_in_diagram.py
ansys/scade/design_rules/modelling/all_constants_types_are_used.py
ansys/scade/design_rules/modelling/all_elements_in_one_equation_set.py
ansys/scade/design_rules/modelling/all_private_operators_are_used.py
ansys/scade/design_rules/modelling/constant_if_then_else.py
ansys/scade/design_rules/modelling/constants_have_const_pragma.py
ansys/scade/design_rules/modelling/disadvised_operators.py
ansys_scade_design_rules-0.2.0.dist-info/licenses/LICENSE
ansys_scade_design_rules-0.2.0.dist-info/WHEEL
ansys_scade_design_rules-0.2.0.dist-info/METADATA
ansys_scade_design_rules-0.2.0.dist-info/RECORD
