Metadata-Version: 2.4
Name: ansys-scade-design-rules
Version: 0.2.0
Summary: Custom SCADE Suite Metrics and Checker's rules.
Keywords: Scade,Python,Rule,Checker
Author-email: "ANSYS, Inc." <pyansys.core@ansys.com>
Maintainer-email: "ANSYS, Inc." <pyansys.core@ansys.com>
Requires-Python: >=3.7,!=3.8.*,!=3.9.*,!=3.11.*
Classifier: Development Status :: 4 - Beta
Classifier: Programming Language :: Python :: 3.7
Classifier: Programming Language :: Python :: 3.10
Classifier: License :: OSI Approved :: MIT License
Classifier: Operating System :: Microsoft :: Windows
License-File: LICENSE
Requires-Dist: importlib-metadata >= 1.0; python_version < '3.8'
Requires-Dist: importlib-metadata >= 4.0; python_version >= '3.8'
Requires-Dist: ansys-scade-apitools >= 0.5
Requires-Dist: defusedxml
Requires-Dist: build==1.2.2.post1 ; extra == "build"
Requires-Dist: twine==6.1.0 ; extra == "build"
Requires-Dist: ansys-sphinx-theme==1.3.2 ; extra == "doc"
Requires-Dist: autodoc_pydantic==2.2.0 ; extra == "doc"
Requires-Dist: jupyter_sphinx==0.5.3 ; extra == "doc"
Requires-Dist: nbsphinx==0.9.7 ; extra == "doc"
Requires-Dist: sphinx==8.1.3 ; extra == "doc"
Requires-Dist: sphinx-autodoc-typehints==3.0.1 ; extra == "doc"
Requires-Dist: sphinxcontrib-globalsubs==0.1.2 ; extra == "doc"
Requires-Dist: sphinxcontrib-httpdomain==1.8.1 ; extra == "doc"
Requires-Dist: sphinx-copybutton==0.5.2 ; extra == "doc"
Requires-Dist: sphinx_design==0.6.1 ; extra == "doc"
Requires-Dist: sphinx-jinja==2.0.2 ; extra == "doc"
Requires-Dist: sphinxnotes-strike==1.2.1 ; extra == "doc"
Requires-Dist: pytest >= 8.3.4 ; extra == "tests" and ( python_version >= '3.8')
Requires-Dist: pytest <= 7.4.4 ; extra == "tests" and ( python_version < '3.8')
Requires-Dist: pytest-cov >= 6.0.0 ; extra == "tests" and ( python_version >= '3.8')
Requires-Dist: pytest-cov <= 4.1.0 ; extra == "tests" and ( python_version < '3.8')
Project-URL: discussions, https://github.com/ansys/scade-design-rules/discussions
Project-URL: documentation, https://design-rules.scade.docs.pyansys.com
Project-URL: homepage, https://www.ansys.com/products/embedded-software/ansys-scade-suite
Project-URL: issues, https://github.com/ansys/scade-design-rules/issues
Project-URL: releases, https://github.com/ansys/scade-design-rules/releases
Project-URL: source, https://github.com/ansys/scade-design-rules
Provides-Extra: build
Provides-Extra: doc
Provides-Extra: tests
